{"hKBmyf+d5GwG9Y465sNhsA==":"service-pic-1-500x335.jpg","pWy830AW9V4iT+ZD/uunJQ==":"si-building-construction_supervision-of-construction_tcm1010-4042_w640_h396_n-600x371.jpg","VEQb6rTUNfz9iuUuWPUR+Q==":"top-best-building-contractors-in-dubai-uae-yellow-pages-directory-600x337.jpg","aZuEia4+peQM55vhAreYVA==":"6470a50ebb49d6f4a4656c72ff0b31f70481b4ea-600x450.jpg","qqFDuWCi7kWu4sdHgPuO+A==":"building_construction_01-1-600x316.jpg","cOfOovryaruwELZyVpGI+w==":"architecture-construction-build-building-162557-600x387.jpg","EA8OPDi1d/brLj2M/cFIQA==":"service-pic-2-500x335.jpg","XSnJk4sWj7UJ+53GCkNjPw==":"image1-350x232.jpg","pVtgecvckwoPcZfOosDFWw==":"malaysia%206-3-26%20kuala%20lumpur%20confluent%201-512x384.jpg","6dDbvWR8p4tTZ6jylW74zg==":"af3ce41e0a14f2552a31fe198edd6580-600x449.jpg","H855AGilxLDA89LCWmglfw==":"cable-laying-contractor-service-500x500.jpg","5JRxHUBxsR7lZaf+f/tCuw==":"twin-culverts-600x266.jpg","y+dtPpjQk3J9JPJtjtkMUA==":"harvest%20ffb-600x450.jpg","s/23XS/w1XMPBTYzr1B4dw==":"pexels-photo-448828%20(1)-1280x853.jpg","HRA9LKjmxOOcXaPllZl3Rg==":"pexels-photo-448828%20(1)-1280x853.jpg","3T5iTmv9q5noSdGX2erasw==":"construction-site-build-construction-work-159358-640x426.jpg","kKgn/igHpvzdD+xNDVhe/w==":"construction-site-build-construction-work-159359-640x426.jpg","arr1AfXIwVqZWk+Y4ceR8Q==":"si-building-construction-supervision-of-construction-tcm1010-4042-w640-h396-n-1-600x371.jpg","pEs7Day5uheM0xbmSCtDog==":"twin-culverts-1-600x266.jpg","SKLdWACin00jBfbHv34+iA==":"calvert-600x450.jpg","958OeCdZdsXYr0t5wUiLww==":"oil%20palm-400x300.jpg","SEXTurGcm9bowAsXxyGTrQ==":"drain-600x396.jpg","7pqE+rE61fm2sU39WFHBQA==":"sump-600x450.jpg","pvDQEPE6PzXkuNn7kKuGVA==":"road-587x440.jpg","So+94f53SwDzVN7810wqBw==":"contractor-600x398.jpg","dazeGKA3BAxsP06d5HqdPw==":"designevo-transparent-500x100.png","rDERtJq6kuhEPQz4MzbcNw==":"designevo-500x100.png","AIYi5uHAVQ6MorvAVbqf1Q==":"designevo-1-500x100.png","oJbC3J6ZlX04mazjxNHFKQ==":"designevo-transparent-200x32.png","J0oS5oGf9LJZxjZ5UJ1cdQ==":"designevo-300x60.jpg","7z8k1iUXV2WFHvYKSZxoUA==":"veev%20int-317x73.png"}